graphic_novel/__init__.py
graphic_novel/actions.py
graphic_novel/character_vn.py
graphic_novel/constants.py
graphic_novel/input_handler.py
graphic_novel/layout_commands.py
tests/__init__.py
tests/actions_test.py
tests/graphic_novel_test.py
tests/parser_test.py
graphic_novel_pyarcade-0.2.0.dist-info/LICENSE
graphic_novel_pyarcade-0.2.0.dist-info/METADATA
graphic_novel_pyarcade-0.2.0.dist-info/WHEEL
graphic_novel_pyarcade-0.2.0.dist-info/top_level.txt
graphic_novel_pyarcade-0.2.0.dist-info/RECORD
