Metadata-Version: 2.1
Name: graphic-novel-pyarcade
Version: 0.2.0
Summary: Little framework to create a graphic novel with python arcade
Home-page: https://github.com/deangelisdf/graphic_novel_pyarcade
Author: Domenico Francesco De Angelis
Author-email: deangelis1993@gmail.com
Project-URL: Bug Reports, https://github.com/deangelisdf/graphic_novel_pyarcade/issues
Project-URL: Source, https://github.com/deangelisdf/graphic_novel_pyarcade
Keywords: graphic novel,game development,arcade
Classifier: Development Status :: 3 - Alpha
Classifier: Intended Audience :: Developers
Classifier: License :: OSI Approved :: MIT License
Classifier: Programming Language :: Python :: 3.6
Classifier: Programming Language :: Python :: 3.7
Classifier: Programming Language :: Python :: 3.8
Classifier: Programming Language :: Python :: 3.9
Classifier: Programming Language :: Python :: 3.10
Classifier: Programming Language :: Python :: 3.11
Classifier: Programming Language :: Python :: 3 :: Only
Requires-Python: >=3.6, <4
License-File: LICENSE
Requires-Dist: arcade
Provides-Extra: dev
Provides-Extra: test
